srt_equalizer/__init__.py
srt_equalizer/srt_equalizer.py
srt_equalizer-0.1.12.dist-info/METADATA
srt_equalizer-0.1.12.dist-info/WHEEL
srt_equalizer-0.1.12.dist-info/licenses/LICENSE
srt_equalizer-0.1.12.dist-info/RECORD
