Metadata-Version: 2.4
Name: srt_equalizer
Version: 0.1.12
Summary: Transform subtitle line lengths, splitting into multiple subtitle fragments if necessary. 
License: MIT
License-File: LICENSE
Author: Peter Krantz
Requires-Python: >=3.8,<4.0
Classifier: License :: OSI Approved :: MIT License
Classifier: Programming Language :: Python :: 3
Classifier: Programming Language :: Python :: 3.8
Classifier: Programming Language :: Python :: 3.9
Classifier: Programming Language :: Python :: 3.10
Classifier: Programming Language :: Python :: 3.11
Classifier: Programming Language :: Python :: 3.12
Classifier: Programming Language :: Python :: 3.13
Classifier: Programming Language :: Python :: 3.14
Requires-Dist: srt (>=3.5.3,<4.0.0)
Project-URL: Repository, https://github.com/peterk/srt_equalizer
